README
setup.py
smithery/__init__.py
smithery.recipe.miners.egg-info/PKG-INFO
smithery.recipe.miners.egg-info/SOURCES.txt
smithery.recipe.miners.egg-info/dependency_links.txt
smithery.recipe.miners.egg-info/entry_points.txt
smithery.recipe.miners.egg-info/namespace_packages.txt
smithery.recipe.miners.egg-info/not-zip-safe
smithery.recipe.miners.egg-info/requires.txt
smithery.recipe.miners.egg-info/top_level.txt
smithery/recipe/__init__.py
smithery/recipe/miners/__init__.py
smithery/recipe/miners/base.py
smithery/recipe/miners/filesystem.py
smithery/recipe/miners/geodata.py
smithery/recipe/miners/google.py
smithery/recipe/miners/tests/__init__.py
smithery/recipe/miners/tests/test_docs.py