Metadata-Version: 1.0
Name: smithery.recipe.miners
Version: 0.3
Summary: A collection of base recipes for metadata extranction
Home-page: http://github.com/alexamici/smithery
Author: Alessandro Amici
Author-email: alexamici@gmail.com
License: ZPL
Platform: UNKNOWN
Classifier: Framework :: Buildout
Classifier: Intended Audience :: Developers
Classifier: Topic :: Software Development :: Build Tools
Classifier: License :: OSI Approved :: Zope Public License
